terraobject/__init__.py
terraobject/terraobject.py
terraobject-0.0.1.dist-info/LICENSE
terraobject-0.0.1.dist-info/METADATA
terraobject-0.0.1.dist-info/WHEEL
terraobject-0.0.1.dist-info/top_level.txt
terraobject-0.0.1.dist-info/RECORD
