Metadata-Version: 2.1
Name: terraobject
Version: 0.0.1
Summary: Terraobject package to share variables between terrascript components
Home-page: https://github.com/byjg/terraobject
Author: Joao Gilberto Magalhaes
Author-email: joao@byjg.com.br
License: MIT
Platform: UNKNOWN
Classifier: Programming Language :: Python :: 3
Classifier: License :: OSI Approved :: MIT License
Classifier: Operating System :: OS Independent
